sessionuser
