Metadata-Version: 1.0
Name: django-session-user
Version: 0.1.1
Summary: Stores the user's information in the session, reucing database queries by a lot.
Home-page: https://github.com/ericflo/django-session-user
Author: Eric Florenzano
Author-email: floguy@gmail.com
License: UNKNOWN
Platform: UNKNOWN
Classifier: Development Status :: 4 - Beta
Classifier: Environment :: Web Environment
Classifier: Intended Audience :: Developers
Classifier: License :: OSI Approved :: BSD License
Classifier: Operating System :: OS Independent
Classifier: Programming Language :: Python
Classifier: Framework :: Django
